currency_rate_bcv/__init__.py
currency_rate_bcv/currency.py
currency_rate_bcv-0.1.0.dist-info/licenses/LICENSE
currency_rate_bcv-0.1.0.dist-info/METADATA
currency_rate_bcv-0.1.0.dist-info/WHEEL
currency_rate_bcv-0.1.0.dist-info/top_level.txt
currency_rate_bcv-0.1.0.dist-info/RECORD
