Metadata-Version: 2.4
Name: currency_rate_bcv
Version: 0.1.0
Summary: Librería para obtener la tasa oficial del Euro y Dólar publicada por el Banco Central de Venezuela (BCV).
Home-page: https://github.com/tuusuario/mi_libreria 
Author: Jarvis Gabriel Huice Padron
Author-email: jarvis.realg@gmail.com
Classifier: Programming Language :: Python :: 3
Classifier: License :: OSI Approved :: MIT License
Classifier: Operating System :: OS Independent
Requires-Python: >=3.6
License-File: LICENSE
Requires-Dist: requests>=2.32.3
Requires-Dist: bs4>=0.0.2
Dynamic: author
Dynamic: author-email
Dynamic: classifier
Dynamic: description
Dynamic: description-content-type
Dynamic: home-page
Dynamic: license-file
Dynamic: requires-dist
Dynamic: requires-python
Dynamic: summary
